MANIFEST.in
README.md
requirements.txt
setup.cfg
setup.py
versioneer.py
botcity/plugins/ms365/onedrive/__init__.py
botcity/plugins/ms365/onedrive/_version.py
botcity/plugins/ms365/onedrive/plugin.py
botcity_ms365_onedrive_plugin.egg-info/PKG-INFO
botcity_ms365_onedrive_plugin.egg-info/SOURCES.txt
botcity_ms365_onedrive_plugin.egg-info/dependency_links.txt
botcity_ms365_onedrive_plugin.egg-info/requires.txt
botcity_ms365_onedrive_plugin.egg-info/top_level.txt
tests/test_import.py
tests/test_plugin.py